google/api/annotations_pb2.py
google/api/annotations_pb2.pyi
google/api/annotations_pb2_grpc.py
google/api/http_pb2.py
google/api/http_pb2.pyi
google/api/http_pb2_grpc.py
speechly/py.typed
speechly/analytics/v1/analytics_api_pb2.py
speechly/analytics/v1/analytics_api_pb2.pyi
speechly/analytics/v1/analytics_api_pb2_grpc.py
speechly/analytics/v1/analytics_pb2.py
speechly/analytics/v1/analytics_pb2.pyi
speechly/analytics/v1/analytics_pb2_grpc.py
speechly/config/v1/config_api_pb2.py
speechly/config/v1/config_api_pb2.pyi
speechly/config/v1/config_api_pb2_grpc.py
speechly/config/v1/model_api_pb2.py
speechly/config/v1/model_api_pb2.pyi
speechly/config/v1/model_api_pb2_grpc.py
speechly/config/v1/model_pb2.py
speechly/config/v1/model_pb2.pyi
speechly/config/v1/model_pb2_grpc.py
speechly/identity/v1/identity_pb2.py
speechly/identity/v1/identity_pb2.pyi
speechly/identity/v1/identity_pb2_grpc.py
speechly/identity/v2/identity_api_pb2.py
speechly/identity/v2/identity_api_pb2.pyi
speechly/identity/v2/identity_api_pb2_grpc.py
speechly/identity/v2/identity_pb2.py
speechly/identity/v2/identity_pb2.pyi
speechly/identity/v2/identity_pb2_grpc.py
speechly/moderation/v1beta1/moderation_api_pb2.py
speechly/moderation/v1beta1/moderation_api_pb2.pyi
speechly/moderation/v1beta1/moderation_api_pb2_grpc.py
speechly/moderation/v1beta1/moderation_pb2.py
speechly/moderation/v1beta1/moderation_pb2.pyi
speechly/moderation/v1beta1/moderation_pb2_grpc.py
speechly/private/project/v1/api_pb2.py
speechly/private/project/v1/api_pb2.pyi
speechly/private/project/v1/api_pb2_grpc.py
speechly/sal/v1/compiler_pb2.py
speechly/sal/v1/compiler_pb2.pyi
speechly/sal/v1/compiler_pb2_grpc.py
speechly/slu/v1/batch_api_pb2.py
speechly/slu/v1/batch_api_pb2.pyi
speechly/slu/v1/batch_api_pb2_grpc.py
speechly/slu/v1/batch_pb2.py
speechly/slu/v1/batch_pb2.pyi
speechly/slu/v1/batch_pb2_grpc.py
speechly/slu/v1/slu_pb2.py
speechly/slu/v1/slu_pb2.pyi
speechly/slu/v1/slu_pb2_grpc.py
speechly/slu/v1/wlu_pb2.py
speechly_api-0.10.4.dist-info/METADATA
speechly_api-0.10.4.dist-info/WHEEL
speechly_api-0.10.4.dist-info/top_level.txt
speechly_api-0.10.4.dist-info/RECORD
