Metadata-Version: 2.1
Name: speechly-api
Version: 0.10.4
Summary: Speechly Public Protobuf Stubs
Home-page: https://github.com/speechly/api/tree/master/python
Author: Speechly
Project-URL: Speechly, https://www.speechly.com/
Project-URL: Source, https://github.com/speechly/api
Keywords: speech,asr,language,nlp
Classifier: Development Status :: 4 - Beta
Classifier: Intended Audience :: Developers
Classifier: Topic :: Software Development :: Build Tools
Classifier: Programming Language :: Python :: 3 :: Only
Requires-Python: >=3.8
Requires-Dist: grpcio >1.50
Requires-Dist: protobuf >3.30
